{
  "_class": "artboard",
  "backgroundColor": {
    "_class": "color",
    "alpha": 1,
    "blue": 1,
    "green": 1,
    "red": 1
  },
  "booleanOperation": -1,
  "clippingMaskMode": 0,
  "do_objectID": "D09CACB2-7C40-4E92-ACF9-960967E73A55",
  "exportOptions": {
    "_class": "exportOptions",
    "exportFormats": [
    ],
    "includedLayerIds": [
    ],
    "layerOptions": 0,
    "shouldTrim": false
  },
  "frame": {
    "_class": "rect",
    "constrainProportions": false,
    "height": 922,
    "width": 360,
    "x": -1600,
    "y": -1330
  },
  "hasBackgroundColor": false,
  "hasClickThrough": false,
  "hasClippingMask": false,
  "horizontalRulerData": {
    "_class": "rulerData",
    "base": 0,
    "guides": [
    ]
  },
  "includeBackgroundColorInExport": true,
  "includeInCloudUpload": true,
  "isFixedToViewport": false,
  "isFlippedHorizontal": false,
  "isFlippedVertical": false,
  "isFlowHome": false,
  "isLocked": false,
  "isVisible": true,
  "layerListExpandedType": 2,
  "layers": [
    {
      "class": "rectangle",
      "id": "BC221B1A-0665-4A34-9767-6AAC0545036C"
    },
    {
      "class": "rectangle",
      "id": "97B5EC98-6BBE-4556-8F4B-0F5C4F38D85F"
    },
    {
      "class": "symbolInstance",
      "id": "E997D202-C42E-4F72-BB80-D0C29D212A39"
    },
    {
      "class": "group",
      "id": "FCD8A400-8895-4DB0-8D9F-334DAA0BC07E"
    },
    {
      "class": "symbolInstance",
      "id": "22AB1EFB-D39F-40C4-A050-157F89573CA3"
    }
  ],
  "layout": {
    "_class": "layoutGrid",
    "columnWidth": 61.5,
    "drawHorizontal": true,
    "drawHorizontalLines": false,
    "drawVertical": true,
    "gutterHeight": 8,
    "gutterWidth": 24,
    "guttersOutside": false,
    "horizontalOffset": 21,
    "isEnabled": true,
    "numberOfColumns": 4,
    "rowHeightMultiplication": 1,
    "totalWidth": 318
  },
  "name": "MOBILE",
  "nameIsFixed": false,
  "presetDictionary": {
    "allowResizedMatching": 0,
    "height": 640,
    "name": "MOBILE",
    "offersLandscapeVariant": 0,
    "width": 360
  },
  "resizesContent": false,
  "resizingConstraint": 63,
  "resizingType": 0,
  "rotation": 0,
  "shouldBreakMaskChain": true,
  "style": {
    "_class": "style",
    "endMarkerType": 0,
    "miterLimit": 10,
    "startMarkerType": 0,
    "windingRule": 1
  },
  "verticalRulerData": {
    "_class": "rulerData",
    "base": 0,
    "guides": [
    ]
  }
}