{
  "_class": "shapeGroup",
  "clippingMaskMode": 0,
  "do_objectID": "3A177FF4-3A50-4643-9CBB-FC4D19FC91C4",
  "exportOptions": {
    "_class": "exportOptions",
    "exportFormats": [
    ],
    "includedLayerIds": [
    ],
    "layerOptions": 0,
    "shouldTrim": false
  },
  "frame": {
    "_class": "rect",
    "constrainProportions": false,
    "height": 90,
    "width": 144,
    "x": 432,
    "y": 198
  },
  "hasClickThrough": false,
  "hasClippingMask": false,
  "isFlippedHorizontal": false,
  "isFlippedVertical": false,
  "isLocked": false,
  "isVisible": true,
  "layerListExpandedType": 0,
  "layers": [
    {
      "class": "rectangle",
      "id": "8D62439E-7372-409A-BBC4-F54A9FAFF5BA"
    }
  ],
  "name": "Colour / Green / 20",
  "nameIsFixed": true,
  "resizingConstraint": 18,
  "resizingType": 0,
  "rotation": 0,
  "shouldBreakMaskChain": false,
  "style": {
    "sharedObjectID": "4F44BF3F-D5A1-4F94-BF23-53AE2FF70323"
  },
  "userInfo": {
    "com.animaapp.stc-sketch-plugin": {
      "kModelPropertiesKey": {
      }
    }
  },
  "windingRule": 1
}