{
  "_class": "symbolInstance",
  "booleanOperation": -1,
  "clippingMaskMode": 0,
  "do_objectID": "3E993405-AC1E-4CFF-A58A-25172C1C029A",
  "exportOptions": {
    "_class": "exportOptions",
    "do_objectID": "80F916B9-BA83-4DF6-A3CD-EEA128B0A6F3",
    "exportFormats": [
    ],
    "includedLayerIds": [
    ],
    "layerOptions": 0,
    "shouldTrim": false
  },
  "frame": {
    "_class": "rect",
    "constrainProportions": false,
    "do_objectID": "54536327-BCEE-4D59-846F-C60A9E7CF455",
    "height": 429,
    "width": 560,
    "x": 0,
    "y": 0
  },
  "hasClippingMask": false,
  "horizontalSpacing": 0,
  "isFixedToViewport": false,
  "isFlippedHorizontal": false,
  "isFlippedVertical": false,
  "isLocked": false,
  "isVisible": true,
  "layerListExpandedType": 0,
  "name": "components/cards/image card",
  "nameIsFixed": false,
  "overrideValues": [
  ],
  "resizingConstraint": 63,
  "resizingType": 0,
  "rotation": 0,
  "scale": 1,
  "shouldBreakMaskChain": false,
  "style": {
    "_class": "style",
    "do_objectID": "ABE00AD9-9843-40D7-A13E-1E37C187E68D",
    "endMarkerType": 0,
    "miterLimit": 10,
    "startMarkerType": 0,
    "windingRule": 1
  },
  "symbolID": "1D19C76E-565E-4C90-9481-E28776E96ED4",
  "verticalSpacing": 0
}